pytest_filter_subpackage/__init__.py
pytest_filter_subpackage/plugin.py
pytest_filter_subpackage/version.py
pytest_filter_subpackage-0.2.0.dist-info/LICENSE.rst
pytest_filter_subpackage-0.2.0.dist-info/METADATA
pytest_filter_subpackage-0.2.0.dist-info/WHEEL
pytest_filter_subpackage-0.2.0.dist-info/entry_points.txt
pytest_filter_subpackage-0.2.0.dist-info/top_level.txt
pytest_filter_subpackage-0.2.0.dist-info/RECORD
